README.rst
setup.cfg
setup.py
glim/__init__.py
glim/app.py
glim/cli.py
glim/command.py
glim/commands.py
glim/config.py
glim/controller.py
glim/core.py
glim/exception.py
glim/ext.py
glim/log.py
glim/paths.py
glim/service.py
glim/utils.py
glim.egg-info/PKG-INFO
glim.egg-info/SOURCES.txt
glim.egg-info/dependency_links.txt
glim.egg-info/entry_points.txt
glim.egg-info/requires.txt
glim.egg-info/top_level.txt
glim/prototype/__init__.py
glim/prototype/app/__init__.py
glim/prototype/app/commands.py
glim/prototype/app/controllers.py
glim/prototype/app/routes.py
glim/prototype/app/services.py
glim/prototype/app/start.py
glim/prototype/app/assets/__init__.py
glim/prototype/app/config/__init__.py
glim/prototype/app/config/default.py
glim/prototype/app/config/development.py
glim/prototype/app/storage/__init__.py
glim/test/__init__.py
glim/test/core.py