Metadata-Version: 1.1
Name: glim
Version: 0.11.1
Summary: A modern framework for the web
Home-page: https://github.com/aacanakin/glim
Author: Aras Can Akin
Author-email: aacanakin@gmail.com
License: UNKNOWN
Download-URL: https://github.com/aacanakin/glim/archive/v0.11.1.zip
Keywords: framework,web framework,api development,model view controller,bottle,SQLAlchemy,Jinja2,termcolor
Platform: UNKNOWN
Classifier: Development Status :: 3 - Alpha
Classifier: Environment :: Web Environment
Classifier: Intended Audience :: Developers
Classifier: License :: OSI Approved :: MIT License
Classifier: Operating System :: OS Independent
Classifier: Programming Language :: Python
Classifier: Topic :: Software Development :: Libraries :: Python Modules
